list_dict_DB.py
list_dict_DB-20170911.3.dist-info/DESCRIPTION.rst
list_dict_DB-20170911.3.dist-info/METADATA
list_dict_DB-20170911.3.dist-info/RECORD
list_dict_DB-20170911.3.dist-info/WHEEL
list_dict_DB-20170911.3.dist-info/metadata.json
list_dict_DB-20170911.3.dist-info/top_level.txt
