Metadata-Version: 2.0
Name: list-dict-DB
Version: 20170911.3
Summary: in memory database like object with O(1) queries
Home-page: https://github.com/Jwink3101/list_dict_db
Author: Justin Winokur
Author-email: Jwink3101@gmail.com
License: UNKNOWN
Platform: UNKNOWN
